italianswirls/cli.py
italianswirls/glue.py
italianswirls/server.py
italianswirls-1.1.1.dist-info/METADATA
italianswirls-1.1.1.dist-info/WHEEL
italianswirls-1.1.1.dist-info/entry_points.txt
italianswirls-1.1.1.dist-info/RECORD
