Metadata-Version: 2.1
Name: italianswirls
Version: 1.1.1
Summary: Minimal Python language server based on Jedi
Home-page: https://git.dece.space/Dece/ItalianSwirls
Author: dece
Author-email: shgck@pistache.land
Requires-Python: >=3.8,<3.12
Classifier: Programming Language :: Python :: 3
Classifier: Programming Language :: Python :: 3.8
Classifier: Programming Language :: Python :: 3.9
Classifier: Programming Language :: Python :: 3.10
Classifier: Programming Language :: Python :: 3.11
Requires-Dist: jedi (>=0.19.1,<0.20.0)
Requires-Dist: pygls (>=1.3.1,<2.0.0)
Project-URL: Repository, https://git.dece.space/Dece/ItalianSwirls
